{
    "origin": [
        "/"
    ],
    "responseHeader": [
        "Content-Type"
    ],
    "method": [
        "GET"
    ],
    "maxAgeSeconds": 3600,
    "centra": [
        {
            "centra_ID": "01",
            "naam": "Dienstcentrum Sint-Gerardus",
            "doelgroep": [
                "motorisch",
                "nah"
            ],
            "leeftijdsgroep": [
                "kinderen",
                "jongeren",
                "volwassenen"
            ],
            "beschrijving": "Sint-Gerardus in Diepenbeek biedt onderwijs en zorg op maat voor peuters, kinderen, jongeren en volwassenen met (neuro-)motorische beperkingen. Als school voor buitengewoon basisonderwijs en buitengewoon secundair onderwijs ondersteunen wij ook leerlingen en leerkrachten in het gewone onderwijs door onze ondersteuningsteams voor kinderen en jongeren.",
            "website": "http://www.sintgerardus.be",
            "email": "post@sintgerardus.be",
            "telefoonnummer": "011/35.01.00",
            "adres": "Sint-Gerardusdreef 1, 3590 Diepenbeek",
            "regio": "Limburg"
        },
        {
            "centra_ID": "02",
            "naam": "Heder",
            "doelgroep": [
                "motorisch",
                "nah"
            ],
            "leeftijdsgroep": [
                "kinderen",
                "jongeren",
                "volwassenen"
            ],
            "beschrijving": "Heder biedt zorg en houvast aan personen met een verstandelijke en/of motorische beperking, al dan niet aangeboren. We willen streven naar een maximale integratie in onze maatschappij.",
            "website": "http://www.heder.be",
            "email": "clientonthaal@heder.be",
            "telefoonnummer": "035/40.19.50",
            "adres": "Galjoenstraat 2, 2030 Antwerpen",
            "regio": "Antwerpen"
            },
        {
            "centra_ID": "03",
            "naam": "MFC Sint-Gregorius",
            "doelgroep": [
                "auditief",
                "motorische"
            ],
            "leeftijdsgroep": [
                "jongeren"
            ],
            "beschrijving": "In het Multifunctioneel Centrum worden kinderen en jongeren ondersteund op medisch, paramedisch, psychologisch en pedagogisch vlak. De trajecten zijn gebaseerd op de modules verblijf, dagopvang, dagbesteding en mobiele/ambulante begeleiding.",
            "website": "http://www.mfcsintgregorius.be",
            "email": "gregorius.mfc@fracarita.org",
            "telefoonnummer": "092/10.00.00",
            "adres": "Jules Destréelaan 67, 50 Gentbrugge",
            "regio": "West-Vlaanderen"
        },
        {
            "centra_ID": "04",
            "naam": "KIDS",
            "doelgroep": [
                "auditief",
                "taal"
               
            ],
            "leeftijdsgroep": [
                "kinderen",
                "jongeren",
                "volwassenen"
            ],
            "beschrijving": "Wij werken vanuit hartelijke professionaliteit met jou en jouw netwerk samen op 5 verschillende vestigingsplaatsen in Limburg en Vlaams Brabant. Wij willen een kennis en expertisecentrum zijn waarop jij als kind of volwassene en jouw context beroep kunnen doen zodat je je maximaal kan ontplooien. Wij ondersteunen ook graag andere diensten.",
            "website": "http://ww.kids.be",
            "email": "kids@kids.be",
            "telefoonnummer": "011/22.25.93",
            "adres": "broggravevijverstraat 9, 3500 Hasselt",
            "regio": "Limburg"
        },
        {
            "centra_ID": "05",
            "naam": "OC De Beweging",
            "doelgroep": [
                "motorisch"
            ],
            "leeftijdsgroep": [
                "volwassenen"
            ],
            "beschrijving": "Het OC De Beweging heeft een breed aanbod aan zorg en ondersteuning, met een uitgesproken expertise in de ondersteuning van personen met een fysieke beperking, NAH (niet-aangeboren hersenletsel) en neurodegeneratieve ziekten. ",
            "website": "http://www.ocdebeweging.be",
            "email": "de.beweging@fracarita.org",
            "telefoonnummer": "092/10.00.00",
            "adres": "Brielstraat 46, 9860 Gijzenzele",
            "regio": "Oost-Vlaanderen"
        },
        {
            "centra_ID": "06",
            "naam": "Spermalie",
            "doelgroep": [
                "visueel",
                "auditief",
                "taal"
            ],
            "leeftijdsgroep": [
                "kinderen",
                "jongeren",
                "volwassevonen"
            ],
            "beschrijving": "Campus Spermalie gaat voor een inclusieve samenleving waarin mensen met een beperking gelijke hebben. Ook als dat gespecialiseerde ondersteuning vergt. Want expertise in zorg en onderwijs maakt voor veel kinderen en jongeren en volwassenen een wereld van verschil.",
            "website": "http://www.de-kade.org",
            "email": "bc-spermalie@de-kade.be",
            "telefoonnummer": "050/34.03.41",
            "adres": "broggravevijverstraat 9, 3500 Hasselt",
            "regio": [
                "West-Vlaanderen",
                "Oost-Vlaanderen",
                "Limburg"
                ]
        },
        {
            "centra_ID": "07",
            "naam": "Ganspoel",
            "doelgroep": [
                "visueel",
                "nah"
            ],
            "leeftijdsgroep": [
                "kinderen",
                "jongeren",
                "volwassenen"
            ],
            "beschrijving": "Centrum Ganspoel biedt ondersteuning aan kinderen en jongeren en volwassenen met een visuele of meervoudige beperking. We werken daarbij nauw samen met de ouders en het netwerk van onze cliënten.",
            "website": "http://www.ganspoel.be",
            "email": "admin@ganspoel.be",
            "telefoonnummer": "026/86.00.40",
            "adres": "Ganspoel 2, 3040 Huldenberg",
            "regio": [
                "Antwerpen",
                "Brussel",
                "Limburg",
                "Oost-Vlaanderen",
                "Vlaams-Brabant"
            ]
        },
        {
            "centra_ID": "08",
            "naam": "Huize Walden",
            "doelgroep": [
                "motorisch"
            ],
            "leeftijdsgroep": [
                "jongeren",
                "volwassenen"
            ],
            "beschrijving": "Huize Walden is een warme zorgorganisatie voor personen met een zorgvraag. Met onze ligging in de schaduw van de abdij van Westmalle doen we een uitgebreid aanbod van kwalitatieve zorg. Je kan in Huize Walden terecht met al je vragen rond wonen, dagbesteding, ambulante- en mobiele begeleiding,Rechtstreeks Toegankelijke Hulpverlening (Rth), vakantie, ... en nog veel meer. ",
            "website": "http://www.huizewalden.be",
            "email": "info@huizewalden.be",
            "telefoonnummer": "033/12.23.92",
            "adres": "Sint Pauluslaan 12, 2390 Malle",
            "regio": "Antwerpen"
        },
        {
            "centra_ID": "09",
            "naam": "Windekind",
            "doelgroep": [
                "motorisch"
            ],
            "leeftijdsgroep": [
                "kinderen"
            ],
            "beschrijving": "Bij Windekind Leuven willen we ons samen met u 100% inzetten voor de opvoeding en het onderwijs van uw kind. We willen dat ieder kind zich bij ons thuis voelt. Van daaruit bouwen we (buitengewone) ondersteuning uit voor uw kind. Elk kind met zijn eigen mogelijkheden en beperktheden helpen we om volgens zijn eigen tempo te ontwikkelen. We werken daarbij graag met u samen! ",
            "website": "http://www.windekindleuven.be",
            "email": "vzw@windekindleuven.b",
            "telefoonnummer": "016/24.11.10",
            "adres": "Schapenstraat 98, 3000 Leuven",
            "regio": "Vlaams-Brabant"
        },
        {
            "centra_ID": "10",
            "naam": "Koninklijk Instituut Woluwe",
            "doelgroep": [
                "visueel",
                "auditief",
                "taal"
            ],
            "leeftijdsgroep": [
                "kinderen",
                "jongeren"
            ],
            "beschrijving": "Binnen het Koninklijk Instituut Woluwe staan verschillende gespecialiseerde diensten klaar om onderwijs en zorg te bieden aan kinderen en volwassenen (vanaf 0 jaar) met een auditieve beperking of met een spraak-taalontwikkelingsstoornis of aan jongeren (12-18 jaar) met een visuele beperking. Deze diensten zijn een school voor buitengewoon basisonderwijs, een school voor Buitengewoon Secundair Onderwijs, een multifunctioneel centrum, een thuisbegeleidingsdienst en een revalidatiecentrum.",
            "website": "http://www.kiwoluwe.org",
            "email": "info@kiwoluwe.org",
            "telefoonnummer": "027/35.40.85",
            "adres": "Georges Henrilaan 278, 1200 Sint-Lambrechts-Woluwe",
            "regio": "Brussel"
        },
        {
            "centra_ID": "11",
            "naam": "Licht en Liefde",
            "doelgroep": [
                "visueel"
                
            ],
            "leeftijdsgroep": [
                "kinderen",
                "jongeren",
                "volwassenen"
            ],
            "beschrijving": "Licht en Liefde. Helemaal voor jou. Als slecht tot niet zien jouw realiteit is. Door onze gerichte feedback en directe aanpak kun je snel een nieuwe start nemen. Ons teams van beroepskrachten, vrijwilligers en ervaringsgenoten doen er alles aan om je concreet te informeren, te adviseren en te ondersteunen. We kennen de kansen maar ook de struikelblokken en kijken , samen met jou, hoe we die van de baan krijgen. Zo snel mogelijk dat spreekt voor zich. ",
            "website": "https://www.blindenzorglichtenliefde.be/",
            "email": "alg.dir@lichtenliefde.be",
            "telefoonnummer": "050/40.60.50",
            "adres": "Oudenburgweg 40, 8490 Varsenare",
            "regio": [
                "Brussel",
                "Limburg",
                "Antwerpen",
                "West-Vlaanderen",
                "Oost-Vlaanderen",
                "Vlaams-Brabant"
            ]
        },
        {
            "centra_ID": "12",
            "naam": "Dominiek Savio vzw",
            "doelgroep": [
                "motorisch",
                "nah"
                
            ],
            "leeftijdsgroep": [
                "kinderen",
                "jongeren",
                "volwassenen"
            ],
            "beschrijving": "Dominiek Savio ondersteunt baby's, kinderen, jongeren en volwassenen met een (neuro-)motorische handicap of een niet aangeboren hersenletsel (NAH). De organisatie biedt oplossingen op het vlak van onderwijs, wonen, dagbesteding, praktische hulp, thuisbegeleiding... De ondersteuning vindt plaats in de eigen omgeving of in ons centrum.",
            "website": "http://dominiek-savio.be",
            "email": "info@dominiek-savio.be",
            "telefoonnummer": "051/23.06.11",
            "adres": "Koolskampstraat 24, 8830 Gits",
            "regio": [ "West-Vlaanderen"
            ]
        }
    ]
}